aiogrpctools-1.0.2.dist-info/METADATA
aiogrpctools-1.0.2.dist-info/RECORD
aiogrpctools-1.0.2.dist-info/WHEEL
aiogrpctools/__init__.py
aiogrpctools/base.py
