Metadata-Version: 2.1
Name: aiogrpctools
Version: 1.0.2
Author: Pasha Podolsky
Author-email: ppodolsky@me.com
Home-page: https://github.com/izihawa/aiogrpctools
License: MIT License
Classifier: Programming Language :: Python :: 3.8
Requires-Python: >=3.8
Requires-Dist: aiokit
Requires-Dist: grpcio
Requires-Dist: izihawa-configurator
Requires-Dist: izihawa-loglib
Requires-Dist: izihawa-utils
Requires-Dist: protobuf
Requires-Dist: pyyaml
